CHANGES.txt
MANIFEST.in
README.md
README.rst
setup.cfg
setup.py
docs/doc.txt
smw/SemanticMediaWiki.py
smw/__init__.py
smw.egg-info/PKG-INFO
smw.egg-info/SOURCES.txt
smw.egg-info/dependency_links.txt
smw.egg-info/requires.txt
smw.egg-info/top_level.txt