Metadata-Version: 1.1
Name: smw
Version: 0.1.3.1
Summary: Semantic Mediawiki Python Binding
Home-page: https://github.com/baojie/smw
Author: Jie Bao
Author-email: baojie@gmail.com
License: License :: OSI Approved :: Python Software Foundation License
Platform: UNKNOWN
Classifier: Development Status :: 3 - Alpha
Classifier: Intended Audience :: Developers
Classifier: Intended Audience :: System Administrators
Classifier: License :: OSI Approved :: Python Software Foundation License
Classifier: Programming Language :: Python
Classifier: Programming Language :: Python :: 2
